{
	"list": [{
			"name": "How to train your dragon: The Hidden World",
			"img": "'/img/moimg/1c.jpg'",
			"year": "2019",
			"lang": "ENG",
			"play": "https://jxjjxy-my.sharepoint.com/:u:/g/personal/dsznwgkc_m_mzr_me/ETJoqNgbLjFCmTYYWf5NuhcByWFnMvsSCF_08nTvkOp_xA?e=EJyvQG&download=1"
		},
		{
			"name": "Reign of the Supermen",
			"img": "'/img/moimg/2c.jpg'",
			"year": "2019",
			"lang": "ENG",
			"play": "https://jxjjxy-my.sharepoint.com/:u:/g/personal/dsznwgkc_m_mzr_me/Ed_itL3iv_tIrZFkfXZROp8BEijXgFZD8BEAxPjQtnUVmQ?e=y9p2gZ&download=1"
		},
		{
			"name": "The LEGO Movie 2: The Second Part",
			"img": "'/img/moimg/3c.jpg'",
			"year": "2019",
			"lang": "ENG",
			"play": "https://jxjjxy-my.sharepoint.com/:u:/g/personal/dsznwgkc_m_mzr_me/ETrIB0Vi02BLsdRTPOCMq18Bvz-udnutxlu_nZ7dvmODxw?e=STTcZh&download=1"
		},
		{
			"name": "The Queen's Corgi",
			"img": "'/img/moimg/4c.jpg'",
			"year": "2019",
			"lang": "ENG",
			"play": "https://jxjjxy-my.sharepoint.com/:u:/g/personal/dsznwgkc_m_mzr_me/EbjyKlZp1YZBhAzLA2TVNikBXjy2btZ26_KC6wa0gTVvDw?e=LaFhgR&download=1"
		},
		{
			"name": "Wonder Park",
			"img": "'/img/moimg/5c.jpg'",
			"year": "2019",
			"lang": "ENG",
			"play": "https://jxjjxy-my.sharepoint.com/:u:/g/personal/dsznwgkc_m_mzr_me/EZxZ1sT3-_1NlcetqxBjcm0BNIqogqvCFkvM0CKVmAwZUw?e=AMd2hd&download=1"
		},
		{
			"name": "Justice League vs the Fatal Five",
			"img": "'/img/moimg/6c.jpg'",
			"year": "2019",
			"lang": "ENG",
			"play": "https://jxjjxy-my.sharepoint.com/:u:/g/personal/dsznwgkc_m_mzr_me/EUXzuD-5TyZNo0RBiycMR_IB3q6Ae9GOCF8r9Nu5mpaTuQ?e=PoGg2j&download=1"
		},
		{
			"name": "Missing Link",
			"img": "'/img/moimg/7c.jpg'",
			"year": "2019",
			"lang": "ENG",
			"play": "https://jxjjxy-my.sharepoint.com/:u:/g/personal/dsznwgkc_m_mzr_me/EXXFF3ZUvpZHko8i5rKvEmgBRkG22F5WqDONMRKirHElUA?e=lcVufo&download=1"
		},
		{
			"name": "Uglydolls",
			"img": "'/img/moimg/8c.jpg'",
			"year": "2019",
			"lang": "ENG",
			"play": "https://jxjjxy-my.sharepoint.com/:u:/g/personal/dsznwgkc_m_mzr_me/EdS4lLO4qZVJk4sdzZhZtMgBHoa1TUFYrr6BusHZnAglTQ?e=b7phuU&download=1"
		},
		{
			"name": "The Secret Life of Pets 2",
			"img": "'/img/moimg/9c.jpg'",
			"year": "2019",
			"lang": "ENG",
			"play": "https://jxjjxy-my.sharepoint.com/:u:/g/personal/dsznwgkc_m_mzr_me/Eemx_8Xfs_hGqNZbEyDGzEYBCX1tC8Zq5c0tTl_C--GJjA?e=Gyl18L&download=1"
		},
		{
			"name": "Toy Story 4",
			"img": "'/img/moimg/10c.jpg'",
			"year": "2019",
			"lang": "ENG",
			"play": "https://jxjjxy-my.sharepoint.com/:u:/g/personal/dsznwgkc_m_mzr_me/Ea1Cmy1DouJGjAHhxfTu3k0B5RMhTD7EOaq4SaX2-l_tdg?e=o34ego&download=1"
		},
		{
			"name": "The Lion King",
			"img": "'/img/moimg/11c.jpg'",
			"year": "2019",
			"lang": "ENG",
			"play": "https://jxjjxy-my.sharepoint.com/:u:/g/personal/dsznwgkc_m_mzr_me/ETz-GF7aibRPqa0ygCGcQncBKauI5IyXymvBW3UFjthRgQ?e=rRbD48&download=1"
		},
		{
			"name": "Red Shoes & the 7 Dwarfs",
			"img": "'/img/moimg/12c.jpg'",
			"year": "2019",
			"lang": "ENG",
			"play": "https://jxjjxy-my.sharepoint.com/:u:/g/personal/dsznwgkc_m_mzr_me/ETG-s9QKKDxDhGzeIMo8f1EBHp60G7Jwtuoip2Vo8pJfdQ?e=1yKnaG&download=1"
		},
		{
			"name": "The Angry Birds Movie 2",
			"img": "'/img/moimg/13c.jpg'",
			"year": "2019",
			"lang": "ENG",
			"play": "https://jxjjxy-my.sharepoint.com/:u:/g/personal/dsznwgkc_m_mzr_me/EWJLv4zt6J5MlE9ZLXXDBCQBrbweTba0_SB5CZwhZdI_Dw?e=gpI9m5&download=1"
		},
		{
			"name": "Playmobil: The Movie",
			"img": "'/img/moimg/14c.jpg'",
			"year": "2019",
			"lang": "ENG",
			"play": "https://jxjjxy-my.sharepoint.com/:u:/g/personal/dsznwgkc_m_mzr_me/EdwG7-spJ5FKgkUd-FRCc3ABT0JupgG8VwRWJXv8w1ii0A?e=YqJSEJ&download=1"
		},
		{
			"name": "One Piece: Stampede",
			"img": "'/img/moimg/15c.jpg'",
			"year": "2019",
			"lang": "ENG",
			"play": "https://jxjjxy-my.sharepoint.com/:u:/g/personal/dsznwgkc_m_mzr_me/ER7ECuGrsBFHuNZTn--ACKQB7WjQekOjTME8mZbr4gI-6Q?e=63ysqO&download=1"
		},
		{
			"name": "Abominable",
			"img": "'/img/moimg/16c.jpg'",
			"year": "2019",
			"lang": "ENG",
			"play": "https://jxjjxy-my.sharepoint.com/:u:/g/personal/dsznwgkc_m_mzr_me/EcaKfVG49FZGgPR32yp-QFsBChs3ZApyJ4hbCDbZiS9rGA?e=DAAmky&download=1"
		},
		{
			"name": "Shaun the Sheep Movie: Farmageddon",
			"img": "'/img/moimg/17c.jpg'",
			"year": "2019",
			"lang": "ENG",
			"play": "https://jxjjxy-my.sharepoint.com/:u:/g/personal/dsznwgkc_m_mzr_me/ESEw6vcvSjpEukExQiP7K6gBkMCfzr21YYAWhlAheTsXlw?e=1BPWX0&download=1"
		},
		{
			"name": "Wonder Woman: Bloodlines",
			"img": "'/img/moimg/18c.jpg'",
			"year": "2019",
			"lang": "ENG",
			"play": "https://jxjjxy-my.sharepoint.com/:u:/g/personal/dsznwgkc_m_mzr_me/EQJpehzOt4dEoLxU0A1CxtsBQ7dxdwtW3KVMcD9ACJ8drA?e=PfJFBG&download=1"
		},
		{
			"name": "Arctic Dogs",
			"img": "'/img/moimg/19c.jpg'",
			"year": "2019",
			"lang": "ENG",
			"play": "https://jxjjxy-my.sharepoint.com/:u:/g/personal/dsznwgkc_m_mzr_me/EQY3yQMG6v9EqlwGQUs1Qo0BKk1gxlOdJ-HLmfkopeL2Dw?e=a2aw8F&download=1"
		},
		{
			"name": "I lost My Body",
			"img": "'/img/moimg/20c.jpg'",
			"year": "2019",
			"lang": "ENG",
			"play": "https://jxjjxy-my.sharepoint.com/:u:/g/personal/dsznwgkc_m_mzr_me/EXQiz9OlbaBMi-ql484GrmkB2l4pLk_KBAxlodOENMUq_Q?e=aVAZxL&download=1"
		},
		{
			"name": "Klaus",
			"img": "'/img/moimg/21c.jpg'",
			"year": "2019",
			"lang": "ENG",
			"play": "https://jxjjxy-my.sharepoint.com/:u:/g/personal/dsznwgkc_m_mzr_me/EWuFaDQIFxxAsStIXtJj_W4BRAqbOPa-7QConMX9KH5wEQ?e=KbZvmi&download=1"
		},
		{
			"name": "Frozen 2",
			"img": "'/img/moimg/22c.jpg'",
			"year": "2019",
			"lang": "ENG",
			"play": "https://jxjjxy-my.sharepoint.com/:u:/g/personal/dsznwgkc_m_mzr_me/Ee2PTYjNY5VIrFr_6KS38WIBw6vFwyb7GCvhxLCuCaG4vg?e=W5SNmG&download=1"
		},
		{
			"name": "Spies in Disguise",
			"img": "'/img/moimg/23c.jpg'",
			"year": "2019",
			"lang": "ENG",
			"play": "https://jxjjxy-my.sharepoint.com/:u:/g/personal/dsznwgkc_m_mzr_me/EVBeMMi4KsJGqGPFqLDlY1wBVOhmh96_JRjYhjKbq3_Ubg?e=lcKRav&download=1"
		},
		{
			"name": "Sonic the Hedgehog",
			"img": "'/img/moimg/24c.jpg'",
			"year": "2020",
			"lang": "ENG",
			"play": "https://jxjjxy-my.sharepoint.com/:u:/g/personal/dsznwgkc_m_mzr_me/EbK7lZL69C1IknEnvL58NtABhS380FTr6WLAO-a74sj4tA?e=OdTIVP&download=1"
		},
		{
			"name": "Onward",
			"img": "'/img/moimg/25c.jpg'",
			"year": "2020",
			"lang": "ENG",
			"play": "https://jxjjxy-my.sharepoint.com/:u:/g/personal/dsznwgkc_m_mzr_me/EZ6gLyvNILZNrRRUSSd6gl4BY1xJpqpbmhJItHtwnbeKXg?e=YjP6aF&download=1"
		},
		{
			"name": "My Hero Academia: Heroes Rising",
			"img": "'/img/moimg/26c.jpg'",
			"year": "2020",
			"lang": "ENG",
			"play": "https://jxjjxy-my.sharepoint.com/:u:/g/personal/dsznwgkc_m_mzr_me/EVC7nr_fHCdLvzeS_fH6Yy0By-wgW1IpXS1hfU75GkIVEQ?e=A2dgRh&download=1"
		},
		{
			"name": "Early Man",
			"img": "'/img/moimg/27c.jpg'",
			"year": "2018",
			"lang": "ENG",
			"play": "https://jxjjxy-my.sharepoint.com/:u:/g/personal/dsznwgkc_m_mzr_me/EQCGFLbYbZtGmunWegrkkYcBXgUmfzTL0fY7YKhHOSDC3Q?e=M8wOiN&download=1"
		},
		{
			"name": "Peter Rabbit",
			"img": "'/img/moimg/28c.jpg'",
			"year": "2018",
			"lang": "ENG",
			"play": "https://jxjjxy-my.sharepoint.com/:u:/g/personal/dsznwgkc_m_mzr_me/ES0ggoYPRARNrzXa8g74XM0BppEGsC4kLQm1JqZt91Ki7Q?e=qC8ZEr&download=1"
		},
		{
			"name": "Sherlock Gnomes",
			"img": "'/img/moimg/29c.jpg'",
			"year": "2018",
			"lang": "ENG",
			"play": "https://jxjjxy-my.sharepoint.com/:u:/g/personal/dsznwgkc_m_mzr_me/EUhhWp20EJdHr0hB7ITq0DoBVPeYE6HSNviJNRBe4WD-FQ?e=JEpaL5&download=1"
		},
		{
			"name": "Isle of Dogs",
			"img": "'/img/moimg/30c.jpg'",
			"year": "2018",
			"lang": "ENG",
			"play": "https://jxjjxy-my.sharepoint.com/:u:/g/personal/dsznwgkc_m_mzr_me/EfLjNillwTtBnyUKuodl3CQBFAYdMzW3-d--eUR46KVRuQ?e=ff3pZN&download=1"
		},
		{
			"name": "White Fang",
			"img": "'/img/moimg/31c.jpg'",
			"year": "2018",
			"lang": "ENG",
			"play": "https://jxjjxy-my.sharepoint.com/:u:/g/personal/dsznwgkc_m_mzr_me/EQ_rxw982OFMugkrx5zkOYABAU6pqrNcwhJCxgnKUS6TCQ?e=4TnlfR&download=1"
		},
		{
			"name": "Cats",
			"img": "'/img/moimg/32c.jpg'",
			"year": "2018",
			"lang": "ENG",
			"play": "https://jxjjxy-my.sharepoint.com/:u:/g/personal/dsznwgkc_m_mzr_me/EaVt7rjZcQpIsVA1dwBm5JsBTi7S2WzUqoO6zxwECXAUjA?e=c7ZmtA&download=1"
		},
		{
			"name": "Charming",
			"img": "'/img/moimg/33c.jpg'",
			"year": "2018",
			"lang": "ENG",
			"play": "https://jxjjxy-my.sharepoint.com/:u:/g/personal/dsznwgkc_m_mzr_me/EYCBllNcul5Nif2vIedGKSEB6K44VvGvrcf00jFuYy_mbA?e=aoUWWd&download=1"
		},
		{
			"name": "Batman Ninja",
			"img": "'/img/moimg/34c.jpg'",
			"year": "2018",
			"lang": "ENG",
			"play": "https://jxjjxy-my.sharepoint.com/:u:/g/personal/dsznwgkc_m_mzr_me/EeK2MnQd9gRBrcfZj2B94TUBW79xf-d4IJyAmGMwryG3Aw?e=rP50fa&download=1"
		},
		{
			"name": "Asterix: The Secret of the Magic Potion",
			"img": "'/img/moimg/35c.jpg'",
			"year": "2018",
			"lang": "ENG",
			"play": "https://jxjjxy-my.sharepoint.com/:u:/g/personal/dsznwgkc_m_mzr_me/EcdVS3CNAJRPlehpjnk_c2EBihF5cqrlk_ptAafZuHBssA?e=afBWJn&download=1"
		},
		{
			"name": "Incredibles 2",
			"img": "'/img/moimg/36c.jpg'",
			"year": "2018",
			"lang": "ENG",
			"play": "https://jxjjxy-my.sharepoint.com/:u:/g/personal/dsznwgkc_m_mzr_me/EcPMRQ2u97FMgrjZdVijxbQBlQ_acf11l8IIl-cR8cewFA?e=rgN20R&download=1"
		},
		{
			"name": "Hotel Transylvania 3: Summer Vacation",
			"img": "'/img/moimg/37c.jpg'",
			"year": "2018",
			"lang": "ENG",
			"play": "https://jxjjxy-my.sharepoint.com/:u:/g/personal/dsznwgkc_m_mzr_me/EaAvP8pZTR5IhfAcr1nSPecB9t_2MNGmdPp48aydhkBTsw?e=0tc8kY&download=1"
		},
		{
			"name": "Mirai",
			"img": "'/img/moimg/38c.jpg'",
			"year": "2018",
			"lang": "ENG",
			"play": "https://jxjjxy-my.sharepoint.com/:u:/g/personal/dsznwgkc_m_mzr_me/EWHpDD4yfoxIul0qafVi8HIBpLdhiVaGcaKBJSWOYbV4kQ?e=dS7poU&download=1"
		},
		{
			"name": "Teen Titans Go! to the Movies",
			"img": "'/img/moimg/39c.jpg'",
			"year": "2018",
			"lang": "ENG",
			"play": "https://jxjjxy-my.sharepoint.com/:u:/g/personal/dsznwgkc_m_mzr_me/EQNU50FHWzFBtTRYhmvnEs0BTwllldR5_Bpg7DuuADmiAA?e=zStTEd&download=1"
		},
		{
			"name": "Christopher Robin",
			"img": "'/img/moimg/40c.jpg'",
			"year": "2018",
			"lang": "ENG",
			"play": "https://jxjjxy-my.sharepoint.com/:u:/g/personal/dsznwgkc_m_mzr_me/EegyfyMAnoVHjLjMFs8TQpcBAdW6wIbafbHgSpaDw6TYlw?e=fcoadP&download=1"
		},
		{
			"name": "My Hero Academia: Two Heroes",
			"img": "'/img/moimg/41c.jpg'",
			"year": "2018",
			"lang": "ENG",
			"play": "https://jxjjxy-my.sharepoint.com/:u:/g/personal/dsznwgkc_m_mzr_me/EYsFOgp5KIRKqZXGsmT2mhQBFRu9pcGEAsKzJmkp508jMg?e=8ldCi0&download=1"
		},
		{
			"name": "I Want to Eat Your Pancreas",
			"img": "'/img/moimg/42c.jpg'",
			"year": "2018",
			"lang": "ENG",
			"play": "https://jxjjxy-my.sharepoint.com/:u:/g/personal/dsznwgkc_m_mzr_me/Ee9oKNRelZBHgnu6Cjbk1QMB4q2iidOUAfgELPRBEaCMMA?e=a1rEU3&download=1"
		},
		{
			"name": "Next Gen",
			"img": "'/img/moimg/43c.jpg'",
			"year": "2018",
			"lang": "ENG",
			"play": "https://jxjjxy-my.sharepoint.com/:u:/g/personal/dsznwgkc_m_mzr_me/Ebkt2blaqPVNtBRer5FnZt0BRy7EpqK-rhXPZYaUNzm0uw?e=ePETD1&download=1"
		},
		{
			"name": "Smallfoot",
			"img": "'/img/moimg/44c.jpg'",
			"year": "2018",
			"lang": "ENG",
			"play": "https://jxjjxy-my.sharepoint.com/:u:/g/personal/dsznwgkc_m_mzr_me/Eby57Cot-I1GkEKaaf8ztUMB2H8gbNqiBiOPYFFwV1ZASg?e=55KCfr&download=1"
		},
		{
			"name": "The Grinch",
			"img": "'/img/moimg/45c.jpg'",
			"year": "2018",
			"lang": "ENG",
			"play": "https://jxjjxy-my.sharepoint.com/:u:/g/personal/dsznwgkc_m_mzr_me/EXaTS4hUiLJFm_n0wnJA8VwBHWYfU7TF3LK1jKab2YBxSw?e=j6nC5o&download=1"
		},
		{
			"name": "Ralph Breaks the Internet: Wreck-It Ralph 2",
			"img": "'/img/moimg/46c.jpg'",
			"year": "2018",
			"lang": "ENG",
			"play": "https://jxjjxy-my.sharepoint.com/:u:/g/personal/dsznwgkc_m_mzr_me/EYe1AHfbRDdJq_FI9-m6RPgBxI0bISTIQYEi_6JCF1wpzg?e=zmKAaa&download=1"
		},
		{
			"name": "Spider-Man: Into the Spider-Verse",
			"img": "'/img/moimg/47c.jpg'",
			"year": "2018",
			"lang": "ENG",
			"play": "https://jxjjxy-my.sharepoint.com/:u:/g/personal/dsznwgkc_m_mzr_me/ETPs5FY3yhhGlqHqgqMkV7EBRJTGdrHPcRfIP7D3RCtDPQ?e=dlmbLq&download=1"
		},
		{
			"name": "Dragon Ball Super: Broly",
			"img": "'/img/moimg/48c.jpg'",
			"year": "2018",
			"lang": "ENG",
			"play": "https://jxjjxy-my.sharepoint.com/:u:/g/personal/dsznwgkc_m_mzr_me/EeKkLPtr-MRFubyccpTLR2sBCBlqhs7LcBmxWaardJpdRA?e=xQ1zXf&download=1"
		},
		{
			"name": "The LEGO Batman Movie",
			"img": "'/img/moimg/49c.jpg'",
			"year": "2017",
			"lang": "ENG",
			"play": "https://jxjjxy-my.sharepoint.com/:u:/g/personal/dsznwgkc_m_mzr_me/Ebk3r4aee-VClAcvyq2VJ0oBjWanxxiUlamP_UWsDYLz-g?e=sIG5BV&download=1"
		},
		{
			"name": "The Boss Baby",
			"img": "'/img/moimg/50c.jpg'",
			"year": "2017",
			"lang": "ENG",
			"play": "https://jxjjxy-my.sharepoint.com/:u:/g/personal/dsznwgkc_m_mzr_me/EaRPV2MUXUdBhLn1FYfUdm0BG1Mr83HNiHOcAntFjyiLfA?e=gnFm84&download=1"
		},
		{
			"name": "Smurfs: The Lost Village",
			"img": "'/img/moimg/51c.jpg'",
			"year": "2017",
			"lang": "ENG",
			"play": "https://jxjjxy-my.sharepoint.com/:u:/g/personal/dsznwgkc_m_mzr_me/ETbecdbhZVZGltohDcvLxOABOqF7imCTGCzJlV5q60CbOA?e=fS1QiG&download=1"
		},
		{
			"name": "Captain Underpants: The First Epic Movie",
			"img": "'/img/moimg/52c.jpg'",
			"year": "2017",
			"lang": "ENG",
			"play": "https://jxjjxy-my.sharepoint.com/:u:/g/personal/dsznwgkc_m_mzr_me/EadKOt6BkihDpvNsHGLv6jcB1VJDeJIOPl1BpSyauc9K0g?e=hOIoOm&download=1"
		},
		{
			"name": "Cars 3",
			"img": "'/img/moimg/53c.jpg'",
			"year": "2017",
			"lang": "ENG",
			"play": "https://jxjjxy-my.sharepoint.com/:u:/g/personal/dsznwgkc_m_mzr_me/EX88vzg9tDtEq5wrGsVx8TEBCS0ODTD7as6T7xJa1tarCQ?e=LFTJuR&download=1"
		},
		{
			"name": "Despicable Me 3",
			"img": "'/img/moimg/54c.jpg'",
			"year": "2017",
			"lang": "ENG",
			"play": "https://jxjjxy-my.sharepoint.com/:u:/g/personal/dsznwgkc_m_mzr_me/ETJWPUERhFVPrLlxFclsdVIBSMgGHtSheTqU0uzF5_0GWA?e=rBTAlR&download=1"
		},
		{
			"name": "Loving Vincent",
			"img": "'/img/moimg/55c.jpg'",
			"year": "2017",
			"lang": "ENG",
			"play": "https://jxjjxy-my.sharepoint.com/:u:/g/personal/dsznwgkc_m_mzr_me/EXArNxL58eNAjGwUVjGlx9YBdtLhVR3ZcGqKaua0kTwVag?e=G9ZCmF&download=1"
		},
		{
			"name": "Mary and the Witch's Flower",
			"img": "'/img/moimg/56c.jpg'",
			"year": "2017",
			"lang": "ENG",
			"play": "https://jxjjxy-my.sharepoint.com/:u:/g/personal/dsznwgkc_m_mzr_me/EeNo1nT4i5JJnIZoorOwXKEBW5KPgMQFF4M8knGVT8orCg?e=6v8VZj&download=1"
		},
		{
			"name": "The Emoji Movie",
			"img": "'/img/moimg/57c.jpg'",
			"year": "2017",
			"lang": "ENG",
			"play": "https://jxjjxy-my.sharepoint.com/:u:/g/personal/dsznwgkc_m_mzr_me/Ed8bDvw4voNFk5M6x97ttnoBEThOElcSzOSdddBieBAXlw?e=oLCTg5&download=1"
		},
		{
			"name": "Batman and Harley Quinn",
			"img": "'/img/moimg/58c.jpg'",
			"year": "2017",
			"lang": "ENG",
			"play": "https://jxjjxy-my.sharepoint.com/:u:/g/personal/dsznwgkc_m_mzr_me/Ee7Sm2lqe2pPhZJX0i7TCwwBWr5f0ES8EZp3jmhoGwcAuQ?e=BVNMDK&download=1"
		},
		{
			"name": "Starship Troopers: Traitor of Mars",
			"img": "'/img/moimg/59c.jpg'",
			"year": "2017",
			"lang": "ENG",
			"play": "https://jxjjxy-my.sharepoint.com/:u:/g/personal/dsznwgkc_m_mzr_me/EWl3vBZDNSZFuLxESH30UTUBMDy44laISvXOMFMwAe1Emg?e=kSbwB6&download=1"
		},
		{
			"name": "The LEGO Ninjago Movie",
			"img": "'/img/moimg/60c.jpg'",
			"year": "2017",
			"lang": "ENG",
			"play": "https://jxjjxy-my.sharepoint.com/:u:/g/personal/dsznwgkc_m_mzr_me/Ecj-BKRuTiJHpfB6LqPS2PcBFbKzzBh_hqe8beJGTsrvFQ?e=2tvig3&download=1"
		},
		{
			"name": "Woody Woodpecker",
			"img": "'/img/moimg/61c.jpg'",
			"year": "2017",
			"lang": "ENG",
			"play": "https://jxjjxy-my.sharepoint.com/:u:/g/personal/dsznwgkc_m_mzr_me/EZYfF1GQlkxKpeDRQypcrOoBZ16mMdvCqcUvaC5UTr_vVg?e=cJjEmU&download=1"
		},
		{
			"name": "My Little Pony: The Movie",
			"img": "'/img/moimg/62c.jpg'",
			"year": "2017",
			"lang": "ENG",
			"play": "https://jxjjxy-my.sharepoint.com/:u:/g/personal/dsznwgkc_m_mzr_me/EcNz7LB18qRPpiwXzHLTC7MBuLRA39dkZyOIXd3HO1n4mw?e=Ft51Uu&download=1"
		},
		{
			"name": "Coco",
			"img": "'/img/moimg/63c.jpg'",
			"year": "2017",
			"lang": "ENG",
			"play": "https://jxjjxy-my.sharepoint.com/:u:/g/personal/dsznwgkc_m_mzr_me/EX5okkkrnEtAjf_LpWsczrwBWP_OhDvlb61cDZ3lRbVgsw?e=mYmzVv&download=1"
		},
		{
			"name": "Paddington 2",
			"img": "'/img/moimg/64c.jpg'",
			"year": "2017",
			"lang": "ENG",
			"play": "https://jxjjxy-my.sharepoint.com/:u:/g/personal/dsznwgkc_m_mzr_me/EQLCK5CQvd5ChFgLGN8xwPYB93SX4YMJz_fjUBlb--Mvgg?e=VZxTo8&download=1"
		},
		{
			"name": "The Star",
			"img": "'/img/moimg/65c.jpg'",
			"year": "2017",
			"lang": "ENG",
			"play": "https://jxjjxy-my.sharepoint.com/:u:/g/personal/dsznwgkc_m_mzr_me/EZIyuLlu0O1OrDAQJSQGkZcBU2KkDv7tp7FmgzTFpwXp0Q?e=ZjIRcU&download=1"
		},
		{
			"name": "The Breadwinner",
			"img": "'/img/moimg/66c.jpg'",
			"year": "2017",
			"lang": "ENG",
			"play": "https://jxjjxy-my.sharepoint.com/:u:/g/personal/dsznwgkc_m_mzr_me/EVl4D7arkjBGo--PnJWvmiABPi_YGLM5qD9BvHGi9WiQHQ?e=mCLdhD&download=1"
		},
		{
			"name": "Ferdinand",
			"img": "'/img/moimg/67c.jpg'",
			"year": "2017",
			"lang": "ENG",
			"play": "https://jxjjxy-my.sharepoint.com/:u:/g/personal/dsznwgkc_m_mzr_me/EWLunnPpSfhKp8eIZQ1yjREBH7it926frOlk5k71U2hT8g?e=PCi6R1&download=1"
		},
		{
			"name": "Kung Fu Panda 3",
			"img": "'/img/moimg/68c.jpg'",
			"year": "2016",
			"lang": "ENG",
			"play": "https://jxjjxy-my.sharepoint.com/:v:/g/personal/dsznwgkc_m_mzr_me/Edm4LLaCge1KrvvkLl150cYBlT0ZpLHyO5NsUMzn3zDUIA?e=w2Ao37&download=1"
		},
		{
			"name": "Zootopia",
			"img": "'/img/moimg/69c.jpg'",
			"year": "2016",
			"lang": "ENG",
			"play": "https://jxjjxy-my.sharepoint.com/:u:/g/personal/dsznwgkc_m_mzr_me/EQsCHQ0nW7dOr3tqwIHiI0UBFtNYqDO0iP5JWziEW0QOQw?e=90rIaG&download=1"
		},
		{
			"name": "The Jungle Book",
			"img": "'/img/moimg/70c.jpg'",
			"year": "2016",
			"lang": "ENG",
			"play": "https://jxjjxy-my.sharepoint.com/:u:/g/personal/dsznwgkc_m_mzr_me/EdKDHCHa34hPtLez2Q8nzdoBvxIBwDCjJVrgLE-6fy1r7A?e=DRjGgD&download=1"
		},
		{
			"name": "The Angry Birds Movie",
			"img": "'/img/moimg/71c.jpg'",
			"year": "2016",
			"lang": "ENG",
			"play": "https://jxjjxy-my.sharepoint.com/:u:/g/personal/dsznwgkc_m_mzr_me/Ee__zQ7jLVJGp0EaQDUucKwBNF99r_HULfwVJUh71gwKUw?e=GJyHtb&download=1"
		},
		{
			"name": "Finding Dory",
			"img": "'/img/moimg/72c.jpg'",
			"year": "2016",
			"lang": "ENG",
			"play": "https://jxjjxy-my.sharepoint.com/:u:/g/personal/dsznwgkc_m_mzr_me/EXbWjaEIUH5EuB26J1hpshQBaqTHIJiDzGGqqNjCoq2OuQ?e=xmiQbm&download=1"
		},
		{
			"name": "The Secret Life of Pets",
			"img": "'/img/moimg/73c.jpg'",
			"year": "2016",
			"lang": "ENG",
			"play": "https://jxjjxy-my.sharepoint.com/:u:/g/personal/dsznwgkc_m_mzr_me/EezqFmYKtjdEjtH7VEhwbhcBkuZ3DaTEx2T27AseL6iKXQ?e=wy2Jua&download=1"
		},
		{
			"name": "Ice Age: Collision Course",
			"img": "'/img/moimg/74c.jpg'",
			"year": "2016",
			"lang": "ENG",
			"play": "https://jxjjxy-my.sharepoint.com/:u:/g/personal/dsznwgkc_m_mzr_me/ESMJMp4Y5c9EnBTvaP_jMysBDBoduDQYPSU9uT1NySzo5Q?e=dMz0qk&download=1"
		},
		{
			"name": "The Red Turtle",
			"img": "'/img/moimg/75c.jpg'",
			"year": "2016",
			"lang": "ENG",
			"play": "https://jxjjxy-my.sharepoint.com/:u:/g/personal/dsznwgkc_m_mzr_me/EWiIekvOVHhPnMzikdfm8hQByq9jKZoB0PiGAn8jaD_2Qw?e=exkelf&download=1"
		},
		{
			"name": "Kingsglaive: Final Fantasy XV",
			"img": "'/img/moimg/76c.jpg'",
			"year": "2016",
			"lang": "ENG",
			"play": "https://jxjjxy-my.sharepoint.com/:u:/g/personal/dsznwgkc_m_mzr_me/EaYyoOYvWV5Ai5Mb3ipin5oBXysR0FlqNT16miNzqXaR5g?e=JozQSI&download=1"
		},
		{
			"name": "Sausage Party",
			"img": "'/img/moimg/77c.jpg'",
			"year": "2016",
			"lang": "ENG",
			"play": "https://jxjjxy-my.sharepoint.com/:u:/g/personal/dsznwgkc_m_mzr_me/EQfLkpv_NRdNiAS-9K9sB3IBB9pM4gtwG7p6rfu4eQRQmg?e=ZVWrDU&download=1"
		},
		{
			"name": "Batman: The Killing Joke",
			"img": "'/img/moimg/78c.jpg'",
			"year": "2016",
			"lang": "ENG",
			"play": "https://jxjjxy-my.sharepoint.com/:u:/g/personal/dsznwgkc_m_mzr_me/EavdZXn6uKdAntUW4TBE1lABjNWCcMJC7XFalf56qE3QbQ?e=htWnYh&download=1"
		},
		{
			"name": "Kubo and the Two Strings",
			"img": "'/img/moimg/79c.jpg'",
			"year": "2016",
			"lang": "ENG",
			"play": "https://jxjjxy-my.sharepoint.com/:u:/g/personal/dsznwgkc_m_mzr_me/EUIv1RfoEsRFv6q5DWQROdYBEP9aimXt69_RUxDM5i-DKQ?e=Yxv4se&download=1"
		},
		{
			"name": "Your Name",
			"img": "'/img/moimg/80c.jpg'",
			"year": "2016",
			"lang": "ENG",
			"play": "https://jxjjxy-my.sharepoint.com/:u:/g/personal/dsznwgkc_m_mzr_me/EcY_fIks8m1Jurju22-D53gBjY-SqHGmJRboG3W6W6U52w?e=VWONcu&download=1"
		},
		{
			"name": "A Silent Voice: The Movie",
			"img": "'/img/moimg/81c.jpg'",
			"year": "2016",
			"lang": "ENG",
			"play": "https://jxjjxy-my.sharepoint.com/:u:/g/personal/dsznwgkc_m_mzr_me/EYSCYnLjps9AhBKoZtHJNsYBcjLtwWe4mPJn_FotdeUSFw?e=8grqDR&download=1"
		},
		{
			"name": "Storks",
			"img": "'/img/moimg/82c.jpg'",
			"year": "2016",
			"lang": "ENG",
			"play": "https://jxjjxy-my.sharepoint.com/:u:/g/personal/dsznwgkc_m_mzr_me/EeC35xFMVIFHo_NyEV5sngQBromYDdQbgfhphnVBv1A8cg?e=pd2Z9b&download=1"
		},
		{
			"name": "My Life as a Zucchini",
			"img": "'/img/moimg/83c.jpg'",
			"year": "2016",
			"lang": "ENG",
			"play": "https://jxjjxy-my.sharepoint.com/:u:/g/personal/dsznwgkc_m_mzr_me/EU-MBRw3g5dCuNMROtkyRz4BFKlMpSgOYxk7Y5QpXlGkqg?e=qnPI1e&download=1"
		},
		{
			"name": "Trolls",
			"img": "'/img/moimg/84c.jpg'",
			"year": "2016",
			"lang": "ENG",
			"play": "https://jxjjxy-my.sharepoint.com/:u:/g/personal/dsznwgkc_m_mzr_me/EfTJsKkARQ1JkFgb0DP0YUwBUBCj6SqALNioyvS_D0Vb-Q?e=Mgc2jc&download=1"
		},
		{
			"name": "Gantz: O",
			"img": "'/img/moimg/85c.jpg'",
			"year": "2016",
			"lang": "ENG",
			"play": "https://jxjjxy-my.sharepoint.com/:u:/g/personal/dsznwgkc_m_mzr_me/EY3PgX_bH4FKlSCsnssa0S8Byb89MjTAh_CURnGx21aUaQ?e=41x5of&download=1"
		},
		{
			"name": "Sing",
			"img": "'/img/moimg/86c.jpg'",
			"year": "2016",
			"lang": "ENG",
			"play": "https://jxjjxy-my.sharepoint.com/:u:/g/personal/dsznwgkc_m_mzr_me/EeWSrxEo_wpPhvg00H5kIyEBWDdEpGTzkGrFWotl7iTfDQ?e=bwRmiE&download=1"
		},
		{
			"name": "Moana",
			"img": "'/img/moimg/87c.jpg'",
			"year": "2016",
			"lang": "ENG",
			"play": "https://jxjjxy-my.sharepoint.com/:u:/g/personal/dsznwgkc_m_mzr_me/ETKFEKzdsplKsiNZj4OVjLABmc8lPRsVeLC-NWjR0KCyWg?e=Tq5ncW&download=1"
		},
		{
			"name": "Leap!",
			"img": "'/img/moimg/88c.jpg'",
			"year": "2016",
			"lang": "ENG",
			"play": "https://jxjjxy-my.sharepoint.com/:u:/g/personal/dsznwgkc_m_mzr_me/EaDSQOQnDmlAnMJcquahtkEBJMuT6dJk7uL1R3bR4Y1tWQ?e=bJdwqe&download=1"
		},
		{
			"name": "Monster Trucks",
			"img": "'/img/moimg/89c.jpg'",
			"year": "2016",
			"lang": "ENG",
			"play": "https://jxjjxy-my.sharepoint.com/:u:/g/personal/dsznwgkc_m_mzr_me/EXoSJqdA_PFGreF-blkGZGIBb9P7V17GcDDJawVYCI2WBw?e=2Nf0tM&download=1"
		},
		{
			"name": "Trolls World Tour",
			"img": "'/img/moimg/90c.jpg'",
			"year": "2020",
			"lang": "ENG",
			"play": "https://jxjjxy-my.sharepoint.com/:u:/g/personal/dsznwgkc_m_mzr_me/EXkJfQunJxNIqJpbmJvIyCUBePmQOs7ZwKZ0vRQcdpZ2DQ?e=JlOv0u&download=1"
		},
		{
			"name": "Ella Bella Bingo",
			"img": "'/img/moimg/91c.jpg'",
			"year": "2020",
			"lang": "ENG",
			"play": "https://jxjjxy-my.sharepoint.com/:u:/g/personal/dsznwgkc_m_mzr_me/EUYIp2GNdHxDl1m9RPDWJFsB3g7Mnf766H-3e6Y9XNCjHw?e=Zzhsrc&download=1"
		},
		{
			"name": "Superman: Red Son",
			"img": "'/img/moimg/92c.jpg'",
			"year": "2020",
			"lang": "ENG",
			"play": "https://jxjjxy-my.sharepoint.com/:u:/g/personal/dsznwgkc_m_mzr_me/Ed9sqCWR9ltPnpiHFQOuVh4BQLlrGCdJELGf9kYCUQ512g?e=bi7lm8&download=1"
		},
		{
			"name": "Manou the Swift",
			"img": "'/img/moimg/93c.jpg'",
			"year": "2019",
			"lang": "ENG",
			"play": "https://jxjjxy-my.sharepoint.com/:u:/g/personal/dsznwgkc_m_mzr_me/EeGKnULmlbxFmGU38sd4DGgBTcetMTPRDNZ-2WckbVoiTg?e=EfMiPS&download=1"
		},
		{
			"name": "The Big Trip",
			"img": "'/img/moimg/94c.jpg'",
			"year": "2019",
			"lang": "ENG",
			"play": "https://jxjjxy-my.sharepoint.com/:u:/g/personal/dsznwgkc_m_mzr_me/EUJ6Wr1X1WVCod3VYOSQklUBeUeTdf-QIjsAEiF-co8Fsw?e=ildmhp&download=1"
		},
		{
			"name": "Away",
			"img": "'/img/moimg/95c.jpg'",
			"year": "2019",
			"lang": "ENG",
			"play": "https://jxjjxy-my.sharepoint.com/:u:/g/personal/dsznwgkc_m_mzr_me/ERykAIOfdMFMowi53GU1gmcByvZA3ljU_Nsc8I34i5xMgQ?e=wmeJJw&download=1"
		},
		{
			"name": "White Snake",
			"img": "'/img/moimg/96c.jpg'",
			"year": "2019",
			"lang": "ENG",
			"play": "https://jxjjxy-my.sharepoint.com/:u:/g/personal/dsznwgkc_m_mzr_me/Efa29ijTu1lBn8g1wjw7DroBc7w38SYfXNmzwF23_yZuqg?e=LZtPmI&download=1"
		},
		{
			"name": "Princess Emmy",
			"img": "'/img/moimg/97c.jpg'",
			"year": "2019",
			"lang": "ENG",
			"play": "https://jxjjxy-my.sharepoint.com/:u:/g/personal/dsznwgkc_m_mzr_me/EbxrAGj1q-BGpQ7dijCOvJEB7Rd-FjhZAQDwdRWOdTbL7g?e=iwzDAv&download=1"
		},
		{
			"name": "The Addams Family",
			"img": "'/img/moimg/98c.jpg'",
			"year": "2019",
			"lang": "ENG",
			"play": "https://jxjjxy-my.sharepoint.com/:u:/g/personal/dsznwgkc_m_mzr_me/EYFcir-6LwxPpCRqyyELOTkBeLHDi8xmDQW_ikzc6TB5Og?e=FFrZVh&download=1"
		},
		{
			"name": "The Death and Return of Superman",
			"img": "'/img/moimg/99c.jpg'",
			"year": "2019",
			"lang": "ENG",
			"play": "https://jxjjxy-my.sharepoint.com/:u:/g/personal/dsznwgkc_m_mzr_me/EcPxtfkn0mdEmmznocRNngcBJU1XXiqcHM03nZ3i1Lubww?e=W65kXY&download=1"
		},
		{
			"name": "Fish School 2",
			"img": "'/img/moimg/100c.jpg'",
			"year": "2019",
			"lang": "ENG",
			"play": "https://jxjjxy-my.sharepoint.com/:u:/g/personal/dsznwgkc_m_mzr_me/EbCJw7QwiLhGqTr8or_teVIBqnCWMV3IuOAUiVXn3NjU1g?e=auqJ5M&download=1"
		},
		{
			"name": "Curious George: Royal Monkey",
			"img": "'/img/moimg/101c.jpg'",
			"year": "2019",
			"lang": "ENG",
			"play": "https://jxjjxy-my.sharepoint.com/:u:/g/personal/dsznwgkc_m_mzr_me/EehajEJ8nUJItdwF1zshI94BeKQgpN5uc-eO0YryOcByFA?e=dWRB5z&download=1"
		},
		{
			"name": "To Your Last Death",
			"img": "'/img/moimg/102c.jpg'",
			"year": "2019",
			"lang": "ENG",
			"play": "https://jxjjxy-my.sharepoint.com/:u:/g/personal/dsznwgkc_m_mzr_me/EdOkucOOFWlPsGQMWSGaJn8Bfdtjo6BdQK26I-R8DjHCBg?e=aC55jU&download=1"
		},
		{
			"name": "Steven Universe: The Movie",
			"img": "'/img/moimg/103c.jpg'",
			"year": "2019",
			"lang": "ENG",
			"play": "https://jxjjxy-my.sharepoint.com/:u:/g/personal/dsznwgkc_m_mzr_me/EU32E7dq9l5Kkr74E8_XsVwB6JkV2ZoSAr4E603YMo54qQ?e=uT342J&download=1"
		},
		{
			"name": "Ne Zha",
			"img": "'/img/moimg/104c.jpg'",
			"year": "2019",
			"lang": "ENG",
			"play": "https://jxjjxy-my.sharepoint.com/:u:/g/personal/dsznwgkc_m_mzr_me/Ecoeh6MDUU9CqobYgN9MvPQBpB5wyXgODQZxD60ZbxwQBA?e=guKZQ7&download=1"
		},
		{
			"name": "Invader ZIM: Enter the Florpus",
			"img": "'/img/moimg/105c.jpg'",
			"year": "2019",
			"lang": "ENG",
			"play": "https://jxjjxy-my.sharepoint.com/:u:/g/personal/dsznwgkc_m_mzr_me/Ec7O40IHNytHgdKn1-g2oXQBa5xbqoubmtc6wepNuR4SLw?e=on8TAc&download=1"
		},
		{
			"name": "The Swan Princess: Kingdom of Music",
			"img": "'/img/moimg/106c.jpg'",
			"year": "2019",
			"lang": "ENG",
			"play": "https://jxjjxy-my.sharepoint.com/:u:/g/personal/dsznwgkc_m_mzr_me/Eck2EMdO1AJCmqO48IxFW0UBAuuoTyl_WRlwZMoAnSt0Qg?e=aOdmTX&download=1"
		},
		{
			"name": "Scooby-Doo: Return to Zombie Island",
			"img": "'/img/moimg/107c.jpg'",
			"year": "2019",
			"lang": "ENG",
			"play": "https://jxjjxy-my.sharepoint.com/:u:/g/personal/dsznwgkc_m_mzr_me/EfPL5_25UjxCmqenk3M4Rx4B7QAy-pC-BiYwaMoTnL-yKQ?e=OZE0u7&download=1"
		},
		{
			"name": "Lego DC Batman: Family Matters",
			"img": "'/img/moimg/108c.jpg'",
			"year": "2019",
			"lang": "ENG",
			"play": "https://jxjjxy-my.sharepoint.com/:u:/g/personal/dsznwgkc_m_mzr_me/EVxrLQbKftRMqH1z5nux_S4BpBUZev6IbfnLUoRXlyi6Gg?e=9Qt0kO&download=1"
		},
		{
			"name": "Teen Titans Go! Vs",
			"img": "'/img/moimg/109c.jpg'",
			"year": "2019",
			"lang": "ENG",
			"play": "https://jxjjxy-my.sharepoint.com/:u:/g/personal/dsznwgkc_m_mzr_me/EYylcJQJdsJJv5gndlm3IygBWcbzaA_rn-_-sVWFaNvneg?e=5HL9oe&download=1"
		},
		{
			"name": "Batman: Hush",
			"img": "'/img/moimg/110c.jpg'",
			"year": "2019",
			"lang": "ENG",
			"play": "https://jxjjxy-my.sharepoint.com/:u:/g/personal/dsznwgkc_m_mzr_me/EcE3MiyymFhGv_LwLDvAO9oB_v7wuvDz627T0vrMYSTkKQ?e=eJdSra&download=1"
		},
		{
			"name": "Pokémon: Mewtwo Strikes Back - Evolution",
			"img": "'/img/moimg/111c.jpg'",
			"year": "2019",
			"lang": "ENG",
			"play": "https://jxjjxy-my.sharepoint.com/:u:/g/personal/dsznwgkc_m_mzr_me/EeLv-gVSEBZEjGbDbxl7ExcBx0hs5w6XzuvIadXPib7KjA?e=UJfahF&download=1"
		},
		{
			"name": "Pilgrim's Progress",
			"img": "'/img/moimg/112c.jpg'",
			"year": "2019",
			"lang": "ENG",
			"play": "https://jxjjxy-my.sharepoint.com/:u:/g/personal/dsznwgkc_m_mzr_me/Ec1hLDEkodFIhYhqi33l4nEBo17AYJnrnC-fBpuNDtK3NQ?e=emSFK7&download=1"
		},
		{
			"name": "Batman vs Teenage Mutant Ninja Turtles",
			"img": "'/img/moimg/113c.jpg'",
			"year": "2019",
			"lang": "ENG",
			"play": "https://jxjjxy-my.sharepoint.com/:u:/g/personal/dsznwgkc_m_mzr_me/EVkRrZ3Zs6lAgTLb5QYwcJMBLGsbh-v8p9M4_qgQPgCZog?e=GC4vEG&download=1"
		},
		{
			"name": "Easter Land",
			"img": "'/img/moimg/114c.jpg'",
			"year": "2019",
			"lang": "ENG",
			"play": "https://jxjjxy-my.sharepoint.com/:u:/g/personal/dsznwgkc_m_mzr_me/EWuLUkbYaIVPjVk5z4TlMQMBkQje-lPfxK-H9fGAap-7_w?e=quvRdQ&download=1"
		},
		{
			"name": "Scooby-Doo! and the Curse of the 13th Ghost",
			"img": "'/img/moimg/115c.jpg'",
			"year": "2019",
			"lang": "ENG",
			"play": "https://jxjjxy-my.sharepoint.com/:u:/g/personal/dsznwgkc_m_mzr_me/EVAkJo2LZ11AsUnK6QzhU_0BG0RiFSj37yTHgzujm1Qp3w?e=ukNLs9&download=1"
		},
		{
			"name": "Sheep and Wolves: Pig Deal",
			"img": "'/img/moimg/116c.jpg'",
			"year": "2019",
			"lang": "ENG",
			"play": "https://jxjjxy-my.sharepoint.com/:u:/g/personal/dsznwgkc_m_mzr_me/EbWRPVCQnM9EtgN_CeNB8tkBU_tZ52CPr3IRtc3jHVW1BQ?e=uU1uA9&download=1"
		},
		{
			"name": "Coconut the Little Dragon 2: Into the Jungle",
			"img": "'/img/moimg/117c.jpg'",
			"year": "2019",
			"lang": "ENG",
			"play": "https://jxjjxy-my.sharepoint.com/:u:/g/personal/dsznwgkc_m_mzr_me/EVh04is5dG9Isl3zmCzmCBkB2VC6FLBgqkkdvdr-N7iM_Q?e=uK2GAx&download=1"
		},
		{
			"name": "Astro Kid",
			"img": "'/img/moimg/118c.jpg'",
			"year": "2019",
			"lang": "ENG",
			"play": "https://jxjjxy-my.sharepoint.com/:u:/g/personal/dsznwgkc_m_mzr_me/Efs0dt-zxUZCsIwo7qlZdm8BLOPf47cpBGEchEr-oWZLcQ?e=Yjp9rf&download=1"
		},
		{
			"name": "Spycies",
			"img": "'/img/moimg/119c.jpg'",
			"year": "2020",
			"lang": "ENG",
			"play": "https://jxjjxy-my.sharepoint.com/:u:/g/personal/dsznwgkc_m_mzr_me/EZ9mKz-g7ClBhMJXRwfQCGwBMmRYhKroiUEgklq3IzT9Jg?e=dTKpjP&download=1"
		},
		{
			"name": "Trouble",
			"img": "'/img/moimg/120c.jpg'",
			"year": "2019",
			"lang": "ENG",
			"play": "https://jxjjxy-my.sharepoint.com/:u:/g/personal/dsznwgkc_m_mzr_me/EYAHIh92zWJJgK-MjE20aOEBeTld4ir84x81xlyghH8bDA?e=TDPlaY&download=1"
		},
		{
			"name": "Dragon Quest: Your Story",
			"img": "'/img/moimg/121c.jpg'",
			"year": "2019",
			"lang": "ENG",
			"play": "https://jxjjxy-my.sharepoint.com/:u:/g/personal/dsznwgkc_m_mzr_me/EecnMEy5bfBBvF31Z-YCaNEBBOgxX5BYqlIyGfsLec4AbA?e=H82G6U&download=1"
		},
		{
			"name": "Captain Sabertooth and the Magic Diamond",
			"img": "'/img/moimg/122c.jpg'",
			"year": "2019",
			"lang": "ENG",
			"play": "https://jxjjxy-my.sharepoint.com/:u:/g/personal/dsznwgkc_m_mzr_me/ES94_mVWkpJGuytoU6cqLiEBxWTHnqI24jBvVrRUb1TirQ?e=4LmAa3&download=1"
		},
		{
			"name": "Mosley",
			"img": "'/img/moimg/123c.jpg'",
			"year": "2019",
			"lang": "ENG",
			"play": "https://jxjjxy-my.sharepoint.com/:u:/g/personal/dsznwgkc_m_mzr_me/Ee2hL_IJlpJGpFkYepfxKmIBUut6aluUBGhKhdFX1h79QA?e=76t01R&download=1"
		},
		{
			"name": "Strange Magic",
			"img": "'/img/moimg/124c.jpg'",
			"year": "2015",
			"lang": "ENG",
			"play": "https://jxjjxy-my.sharepoint.com/:u:/g/personal/dsznwgkc_m_mzr_me/Ee5qHVTl7GNCjecXbJx3QB0Bxl9HWJOrB0fFz2kpE8l8FQ?e=T6Av7V&download=1"
		}, {
			"name": "The Spongebob Movie: Sponge Out of Water",
			"img": "'/img/moimg/125c.jpg'",
			"year": "2015",
			"lang": "ENG",
			"play": "https://jxjjxy-my.sharepoint.com/:u:/g/personal/dsznwgkc_m_mzr_me/EUQKStjH_GlHncoH8buIV-8BHVr7-1h-RcrQCSxRMsLhgg?e=EAvTgQ&download=1"
		}, {
			"name": "Shaun the Sheep Movie",
			"img": "'/img/moimg/126c.jpg'",
			"year": "2015",
			"lang": "ENG",
			"play": "https://jxjjxy-my.sharepoint.com/:u:/g/personal/dsznwgkc_m_mzr_me/EQF7_NHO0i1DnkGBJq6aC4kBykPln6VSgM-c0H53rcgRuQ?e=KakZYd&download=1"
		}, {
			"name": "Home",
			"img": "'/img/moimg/127c.jpg'",
			"year": "2015",
			"lang": "ENG",
			"play": "https://jxjjxy-my.sharepoint.com/:u:/g/personal/dsznwgkc_m_mzr_me/ETTd7e01zu9PtDL1OspI66gByAP4HEHRT6nWNkUaLx2iww?e=US4pbE&download=1"
		}, {
			"name": "Inside Out",
			"img": "'/img/moimg/128c.jpg'",
			"year": "2015",
			"lang": "ENG",
			"play": "https://jxjjxy-my.sharepoint.com/:u:/g/personal/dsznwgkc_m_mzr_me/Ed23TstcPBVOgQIiZcsfPuwBXfyhhVsFxoN4h-Dda-SO7Q?e=XeXSbc&download=1"
		}, {
			"name": "Minions",
			"img": "'/img/moimg/129c.jpg'",
			"year": "2015",
			"lang": "ENG",
			"play": "https://jxjjxy-my.sharepoint.com/:u:/g/personal/dsznwgkc_m_mzr_me/EdperobDEJJBpJZcFbULKZMB94xllylFWM5RJmGqXXC_hg?e=VXMZFu&download=1"
		}, {
			"name": "Absolutely Anything",
			"img": "'/img/moimg/130c.jpg'",
			"year": "2015",
			"lang": "ENG",
			"play": "https://jxjjxy-my.sharepoint.com/:u:/g/personal/dsznwgkc_m_mzr_me/EX0GSJuJBClHsQRbx1QWeUcB-kw1AlRcbdSZjjl7RYFckQ?e=LKMV4t&download=1"
		}, {
			"name": "The Boy and the Beast",
			"img": "'/img/moimg/131c.jpg'",
			"year": "2015",
			"lang": "ENG",
			"play": "https://jxjjxy-my.sharepoint.com/:u:/g/personal/dsznwgkc_m_mzr_me/EVxfXIHJliRPqYqMMavK_YkBkdclHZZcbJzZ8fhlakl0FQ?e=bvoFPP&download=1"
		}, {
			"name": "The Little Prince",
			"img": "'/img/moimg/132c.jpg'",
			"year": "2015",
			"lang": "ENG",
			"play": "https://jxjjxy-my.sharepoint.com/:u:/g/personal/dsznwgkc_m_mzr_me/EWK11fGL8lBPs2QlEfkkYbwBOhvn2CPnsMN2k9VmeILv7g?e=E5GRRP&download=1"
		}, {
			"name": "Boruto: Naruto the Movie",
			"img": "'/img/moimg/133c.jpg'",
			"year": "2015",
			"lang": "ENG",
			"play": "https://jxjjxy-my.sharepoint.com/:u:/g/personal/dsznwgkc_m_mzr_me/EYiGCJlsV9ZOh8tH8xJ26ZUB2vY_L70Z8D3eip2CzapX2Q?e=Ax9itW&download=1"
		}, {
			"name": "Hotel Transylvania 2",
			"img": "'/img/moimg/134c.jpg'",
			"year": "2015",
			"lang": "ENG",
			"play": "https://jxjjxy-my.sharepoint.com/:u:/g/personal/dsznwgkc_m_mzr_me/EQ2aZ2ykHB9Pm9PxyowNIqABZzv3ake29YfsJPLOSxvU4A?e=LVp7pr&download=1"
		}, {
			"name": "The Peanuts Movie",
			"img": "'/img/moimg/135c.jpg'",
			"year": "2015",
			"lang": "ENG",
			"play": "https://jxjjxy-my.sharepoint.com/:u:/g/personal/dsznwgkc_m_mzr_me/EXlIrKbslqVAhSoiF-FxD8UB8UPONfQZamGHsEKE7H8rUQ?e=EExy6m&download=1"
		}, {
			"name": "The Good Dinosaur",
			"img": "'/img/moimg/136c.jpg'",
			"year": "2015",
			"lang": "ENG",
			"play": "https://jxjjxy-my.sharepoint.com/:u:/g/personal/dsznwgkc_m_mzr_me/EWjeb_0mQGJLoH7nPevMunAB3FRH5A4g53Q8SIgM01KlaQ?e=US9sWU&download=1"
		}, {
			"name": "Alvin and The Chipmunks: The Road Chip",
			"img": "'/img/moimg/137c.jpg'",
			"year": "2015",
			"lang": "ENG",
			"play": "https://jxjjxy-my.sharepoint.com/:u:/g/personal/dsznwgkc_m_mzr_me/ERAayzUVm0pLrfVha71O1QwBKHxcvFK5AcL_cQIeD3cixg?e=b9Nz2s&download=1"
		}, {
			"name": "Anomalisa",
			"img": "'/img/moimg/138c.jpg'",
			"year": "2015",
			"lang": "ENG",
			"play": "https://jxjjxy-my.sharepoint.com/:u:/g/personal/dsznwgkc_m_mzr_me/EYOk9FhssedMhIAXG2L3v7IBeB83cLXEbObFvh-uL0l2nw?e=Z0FE0x&download=1"
		}, {
			"name": "Mune: Guardian of the Moon",
			"img": "'/img/moimg/139c.jpg'",
			"year": "2014",
			"lang": "ENG",
			"play": "https://jxjjxy-my.sharepoint.com/:u:/g/personal/dsznwgkc_m_mzr_me/ESjCJ3o4CNxEvTt0fZPiSe4BR8Jb8-f2MEdKyTkBaB1uOA?e=J2bEbP&download=1"
		}, {
			"name": "The Lego Movie",
			"img": "'/img/moimg/140c.jpg'",
			"year": "2014",
			"lang": "ENG",
			"play": "https://jxjjxy-my.sharepoint.com/:u:/g/personal/dsznwgkc_m_mzr_me/ER6KqjapJ79CiG4qPxT_makBuZ7qwAeq8ByiAtD2wz9ANA?e=hirk6U&download=1"
		}, {
			"name": "Mr Peabody and Sherman",
			"img": "'/img/moimg/141c.jpg'",
			"year": "2014",
			"lang": "ENG",
			"play": "https://jxjjxy-my.sharepoint.com/:u:/g/personal/dsznwgkc_m_mzr_me/EYUJ5f5oiSpFjxqicx-m2aoBSHU1RH7ALELELQCIJ_ORtg?e=TWEidZ&download=1"
		}, {
			"name": "Rio 2",
			"img": "'/img/moimg/142c.jpg'",
			"year": "2014",
			"lang": "ENG",
			"play": "https://jxjjxy-my.sharepoint.com/:u:/g/personal/dsznwgkc_m_mzr_me/EdwdAabMqjFKkHX_Ps4tkIUB7jUI16rA5gFNIdC07CDknw?e=DGLEUv&download=1"
		}, {
			"name": "How to Train Your Dragon 2",
			"img": "'/img/moimg/143c.jpg'",
			"year": "2014",
			"lang": "ENG",
			"play": "https://jxjjxy-my.sharepoint.com/:u:/g/personal/dsznwgkc_m_mzr_me/EY5vGlLvWo9CuSHywWPhQngBHf0o0TkCknd6-rWt9-u7aQ?e=OWgC4j&download=1"
		}, {
			"name": "When Marnie Was There",
			"img": "'/img/moimg/144c.jpg'",
			"year": "2014",
			"lang": "ENG",
			"play": "https://jxjjxy-my.sharepoint.com/:u:/g/personal/dsznwgkc_m_mzr_me/EQEaJHgSMQ1Hsh4umFjdP6YBeMVIpvMVPO4aFKLxb8S9NQ?e=alc5Wa&download=1"
		}, {
			"name": "Teenage Mutant Ninja Turtles",
			"img": "'/img/moimg/145c.jpg'",
			"year": "2014",
			"lang": "ENG",
			"play": "https://jxjjxy-my.sharepoint.com/:u:/g/personal/dsznwgkc_m_mzr_me/EXTD1c0bi8NBohoZT_pj078BjwSl82kYJYtcbBeITKtTfw?e=hkqkNk&download=1"
		}, {
			"name": "Song of the Sea",
			"img": "'/img/moimg/146c.jpg'",
			"year": "2014",
			"lang": "ENG",
			"play": "https://jxjjxy-my.sharepoint.com/:u:/g/personal/dsznwgkc_m_mzr_me/EW22mkqtO4ZGhsJNfZN03tQB6dBMbMBAjJ9n_uNS5sevkg?e=OferNs&download=1"
		}, {
			"name": "The Boxtrolls",
			"img": "'/img/moimg/147c.jpg'",
			"year": "2014",
			"lang": "ENG",
			"play": "https://jxjjxy-my.sharepoint.com/:u:/g/personal/dsznwgkc_m_mzr_me/EXnSI6zPdIFCvKG0h_OBiC4BrDBOiIFggL5QnwZkJHPLHg?e=E55KzM&download=1"
		}, {
			"name": "The Book of Life",
			"img": "'/img/moimg/148c.jpg'",
			"year": "2014",
			"lang": "ENG",
			"play": "https://jxjjxy-my.sharepoint.com/:u:/g/personal/dsznwgkc_m_mzr_me/EWY6vQZwkbBBpiWDjhW84JUBGaLGF4jv1cNNdusjYCLbQQ?e=z28aTy&download=1"
		}, {
			"name": "Big Hero 6",
			"img": "'/img/moimg/149c.jpg'",
			"year": "2014",
			"lang": "ENG",
			"play": "https://jxjjxy-my.sharepoint.com/:u:/g/personal/dsznwgkc_m_mzr_me/ERQLnAEmOttDlzFRhgpwKVsBgVcNPpUpauzsay_u3XGn1Q?e=n2DhWp&download=1"
		}, {
			"name": "Penguins of Madagascar",
			"img": "'/img/moimg/150c.jpg'",
			"year": "2014",
			"lang": "ENG",
			"play": "https://jxjjxy-my.sharepoint.com/:u:/g/personal/dsznwgkc_m_mzr_me/EWjwiMpJENZPv4rPwIh8gsMBixIHwHXmOJG75ohQiaBrWQ?e=P5M65g&download=1"
		}, {
			"name": "Paddington",
			"img": "'/img/moimg/151c.jpg'",
			"year": "2014",
			"lang": "ENG",
			"play": "https://jxjjxy-my.sharepoint.com/:u:/g/personal/dsznwgkc_m_mzr_me/Eb5nP7AG16RPpO9P7Er4q4YB3m3N2RPKg6Vx1UNgVAuLsg?e=JfF6Tf&download=1"
		}, {
			"name": "The Last: Naruto the Movie",
			"img": "'/img/moimg/152c.jpg'",
			"year": "2014",
			"lang": "ENG",
			"play": "https://jxjjxy-my.sharepoint.com/:u:/g/personal/dsznwgkc_m_mzr_me/EX2UGEwZ5HxLv-OY6CO5tD4BS91IjZHOhLKN01156AbqDA?e=smUK3Z&download=1"
		}, {
			"name": "The Croods",
			"img": "'/img/moimg/153c.jpg'",
			"year": "2013",
			"lang": "ENG",
			"play": "https://jxjjxy-my.sharepoint.com/:u:/g/personal/dsznwgkc_m_mzr_me/ET43gFUjZ09LrUp9VeBGztQB8zGYCZi_OvUY6RVvyE8u9Q?e=ivYhcf&download=1"
		}, {
			"name": "Epic",
			"img": "'/img/moimg/154c.jpg'",
			"year": "2013",
			"lang": "ENG",
			"play": "https://jxjjxy-my.sharepoint.com/:u:/g/personal/dsznwgkc_m_mzr_me/EQ4p9V8W2GdDqQGUhmVxz50BS4-dFtFoU-fEKj2LkkUgbA?e=hhLk42&download=1"
		}, {
			"name": "Monsters University",
			"img": "'/img/moimg/155c.jpg'",
			"year": "2013",
			"lang": "ENG",
			"play": "https://jxjjxy-my.sharepoint.com/:u:/g/personal/dsznwgkc_m_mzr_me/EQMUrZ9-WMBLt55CKBvGUHcBHYrul4MswSE5MIBpvYxS_A?e=XkGQiJ&download=1"
		}, {
			"name": "The Garden of Words",
			"img": "'/img/moimg/156c.jpg'",
			"year": "2013",
			"lang": "ENG",
			"play": "https://jxjjxy-my.sharepoint.com/:u:/g/personal/dsznwgkc_m_mzr_me/EUwvxmxWRqtNlOujICPTx_oBFgDNOTLpZ2YoSMHbIOlojw?e=4g4S2j&download=1"
		}, {
			"name": "Despicable Me 2",
			"img": "'/img/moimg/157c.jpg'",
			"year": "2013",
			"lang": "ENG",
			"play": "https://jxjjxy-my.sharepoint.com/:u:/g/personal/dsznwgkc_m_mzr_me/EUlqnazWxQdIvxUMab7QB2YBVrNpUtOn_tqacrIl7972MQ?e=sThXhN&download=1"
		}, {
			"name": "Turbo",
			"img": "'/img/moimg/158c.jpg'",
			"year": "2013",
			"lang": "ENG",
			"play": "https://jxjjxy-my.sharepoint.com/:u:/g/personal/dsznwgkc_m_mzr_me/EaRQWImL9BRBl6MotIr15S4B6X0wOzGSGTZ-1JbeC08DaA?e=IphRPU&download=1"
		}, {
			"name": "The Wind Rises",
			"img": "'/img/moimg/159c.jpg'",
			"year": "2013",
			"lang": "ENG",
			"play": "https://jxjjxy-my.sharepoint.com/:u:/g/personal/dsznwgkc_m_mzr_me/EYr0m2CC4EJInRMtztqHIA8B3lkPuDYODz5cxmS6Slcf3w?e=HmkGn3&download=1"
		}, {
			"name": "The Smurfs 2",
			"img": "'/img/moimg/160c.jpg'",
			"year": "2013",
			"lang": "ENG",
			"play": "https://jxjjxy-my.sharepoint.com/:u:/g/personal/dsznwgkc_m_mzr_me/EYlEm9GneWdPuhcPHZUYwr4B1gd19yPfMIUkHnu-pssb3g?e=slwp88&download=1"
		}, {
			"name": "Planes",
			"img": "'/img/moimg/161c.jpg'",
			"year": "2013",
			"lang": "ENG",
			"play": "https://jxjjxy-my.sharepoint.com/:u:/g/personal/dsznwgkc_m_mzr_me/Eevuuq0nTcBDhmFsItWcWOoBv74CQ8-pY4Ug91X9J9hvVA?e=3noOtk&download=1"
		}, {
			"name": "Cloudy with a Chance of Meatballs 2",
			"img": "'/img/moimg/162c.jpg'",
			"year": "2013",
			"lang": "ENG",
			"play": "https://jxjjxy-my.sharepoint.com/:u:/g/personal/dsznwgkc_m_mzr_me/EeRNN3z0oZJHqrMLXe_R6KoB8a08s2HmvARZu7RSlC-3ag?e=coZgyS&download=1"
		}, {
			"name": "Tarzan",
			"img": "'/img/moimg/163c.jpg'",
			"year": "2013",
			"lang": "ENG",
			"play": "https://jxjjxy-my.sharepoint.com/:u:/g/personal/dsznwgkc_m_mzr_me/EakKbTiRVSlCrKhOeVLOPgoBkvIvnMRx24rM3OL23hn0TQ?e=fhm4Ue&download=1"
		}, {
			"name": "The Tale of Princess Kaguya",
			"img": "'/img/moimg/164c.jpg'",
			"year": "2013",
			"lang": "ENG",
			"play": "https://jxjjxy-my.sharepoint.com/:u:/g/personal/dsznwgkc_m_mzr_me/EbhGWuq_LT9LmkGqvG79DYUBHr9HF_SA8WoEI11FggvKCQ?e=kmo7op&download=1"
		}, {
			"name": "Frozen",
			"img": "'/img/moimg/165c.jpg'",
			"year": "2013",
			"lang": "ENG",
			"play": "https://jxjjxy-my.sharepoint.com/:u:/g/personal/dsznwgkc_m_mzr_me/EZ_lWuoZRE9OvdcQzhWISUsB8UQc32XXu0QL9DvhBSEqHw?e=E4Icrs&download=1"
		},
		{
			"name": "The Lorax",
			"img": "'/img/moimg/166c.jpg'",
			"year": "2012",
			"lang": "ENG",
			"play": "https://jxjjxy-my.sharepoint.com/:u:/g/personal/dsznwgkc_m_mzr_me/EXErRpNxIfBPv_COkqZEPykBeoY7GiuUGkeTF1dDEDmaEw?e=vREJIS&download=1"
		}, {
			"name": "The Pirates! Band of Misfits",
			"img": "'/img/moimg/167c.jpg'",
			"year": "2012",
			"lang": "ENG",
			"play": "https://jxjjxy-my.sharepoint.com/:u:/g/personal/dsznwgkc_m_mzr_me/EVGcQkpawA1Ju0JYTouoy3MBm-rbr819wQhxK0eAsFxNOg?e=tWDswn&download=1"
		}, {
			"name": "Madagascar 3: Europe's Most Wanted",
			"img": "'/img/moimg/168c.jpg'",
			"year": "2012",
			"lang": "ENG",
			"play": "https://jxjjxy-my.sharepoint.com/:u:/g/personal/dsznwgkc_m_mzr_me/Ef6AMXxfhEJGqtUdS94EaDMBexiJODOzIh9NDNKy3a8ASg?e=4TzlRs&download=1"
		}, {
			"name": "Brave",
			"img": "'/img/moimg/169c.jpg'",
			"year": "2012",
			"lang": "ENG",
			"play": "https://jxjjxy-my.sharepoint.com/:u:/g/personal/dsznwgkc_m_mzr_me/EeuOtl1XUohOsASRG3bI-iABjL8pebLvDYrNlInBlO3iXQ?e=GNWcKZ&download=1"
		}, {
			"name": "Ice Age: Continental Drift",
			"img": "'/img/moimg/170c.jpg'",
			"year": "2012",
			"lang": "ENG",
			"play": "https://jxjjxy-my.sharepoint.com/:u:/g/personal/dsznwgkc_m_mzr_me/EYoxgvoiukVJkCVeym_FrmwBMzWUCUIZwk_Z8pUdS_2N9A?e=uIa1mh&download=1"
		}, {
			"name": "Wolf Children",
			"img": "'/img/moimg/171c.jpg'",
			"year": "2012",
			"lang": "ENG",
			"play": "https://jxjjxy-my.sharepoint.com/:u:/g/personal/dsznwgkc_m_mzr_me/EV06mi3WoN9DrkPtMhmeIdYBQnnOCzqVk1tYmkG1hJH5rA?e=MAc3oh&download=1"
		}, {
			"name": "Starship Troopers: Invasion",
			"img": "'/img/moimg/172c.jpg'",
			"year": "2012",
			"lang": "ENG",
			"play": "https://jxjjxy-my.sharepoint.com/:u:/g/personal/dsznwgkc_m_mzr_me/EaOYX--Tu1xAtN0tmDjwhRgBFtdf6f-rmn7I0bb3uQtOVw?e=b04WKd&download=1"
		}, {
			"name": "ParaNorman",
			"img": "'/img/moimg/173c.jpg'",
			"year": "2012",
			"lang": "ENG",
			"play": "https://jxjjxy-my.sharepoint.com/:u:/g/personal/dsznwgkc_m_mzr_me/EWwTcVLTzEtHmak7x9s90SoB6f1XbVwnZkE54gHi5unoiA?e=yNjlkA&download=1"
		}, {
			"name": "Hotel Transylvania",
			"img": "'/img/moimg/174c.jpg'",
			"year": "2012",
			"lang": "ENG",
			"play": "https://jxjjxy-my.sharepoint.com/:u:/g/personal/dsznwgkc_m_mzr_me/ESboX-wSBllIk5CzrkCGrF8BEudpZujRKDsCumI6N3kRxw?e=X1XHzG&download=1"
		}, {
			"name": "Resident Evil: Damnation",
			"img": "'/img/moimg/175c.jpg'",
			"year": "2012",
			"lang": "ENG",
			"play": "https://jxjjxy-my.sharepoint.com/:u:/g/personal/dsznwgkc_m_mzr_me/EcvS4WhnXFFGjW1i5g19hncBpiqOL2B1Bxvk-m9CgelufQ?e=2XkHoK&download=1"
		}, {
			"name": "Frankenweenie",
			"img": "'/img/moimg/176c.jpg'",
			"year": "2012",
			"lang": "ENG",
			"play": "https://jxjjxy-my.sharepoint.com/:u:/g/personal/dsznwgkc_m_mzr_me/EU1Q0xpZmNFJt1g_dgsnLqMBKqFuUQwzn6HO1iDO1q4iig?e=DFVahK&download=1"
		}, {
			"name": "Wreck-It Ralph",
			"img": "'/img/moimg/177c.jpg'",
			"year": "2012",
			"lang": "ENG",
			"play": "https://jxjjxy-my.sharepoint.com/:u:/g/personal/dsznwgkc_m_mzr_me/ESuZpleO4BBEs6rOlQp3aKIBrClBiA66kKrSfXhqbFZToQ?e=xkenhx&download=1"
		}, {
			"name": "Rise of the Guardians",
			"img": "'/img/moimg/178c.jpg'",
			"year": "2012",
			"lang": "ENG",
			"play": "https://jxjjxy-my.sharepoint.com/:u:/g/personal/dsznwgkc_m_mzr_me/EX5oMVmx-CVJmWq38aAsSPEBkIGzDh5db8UPOU5gbtIJuA?e=cWbkQn&download=1"
		},
		{
			"name": "Happy Feet Two",
			"img": "'/img/moimg/179c.jpg'",
			"year": "2011",
			"lang": "ENG",
			"play": "https://jxjjxy-my.sharepoint.com/:u:/g/personal/dsznwgkc_m_mzr_me/EdPwEIAW1T1FjKEle0eU7TsBnM0SmEsyDEpMEf8pp4ExIg?e=QwawMA&download=1"
		}, {
			"name": "Gnomeo and Juliet",
			"img": "'/img/moimg/180c.jpg'",
			"year": "2011",
			"lang": "ENG",
			"play": "https://jxjjxy-my.sharepoint.com/:u:/g/personal/dsznwgkc_m_mzr_me/EQhyRe0gaehOmmdnAz0t_DwBMu5f8RROgUrSyDMwsCKpgw?e=nu28lk&download=1"
		}, {
			"name": "Rango",
			"img": "'/img/moimg/181c.jpg'",
			"year": "2011",
			"lang": "ENG",
			"play": "https://jxjjxy-my.sharepoint.com/:u:/g/personal/dsznwgkc_m_mzr_me/ETbSlziNwA9JmuALRsgEXYgBn2h3PK0z2p1t6asYUE-64g?e=vpeC4V&download=1"
		}, {
			"name": "Hop",
			"img": "'/img/moimg/182c.jpg'",
			"year": "2011",
			"lang": "ENG",
			"play": "https://jxjjxy-my.sharepoint.com/:u:/g/personal/dsznwgkc_m_mzr_me/EQk0j0cCSRZGsau5NJLRyyABiVnJVoVtGW5bzivsTSDyXw?e=k8MxRE&download=1"
		}, {
			"name": "Rio",
			"img": "'/img/moimg/183c.jpg'",
			"year": "2011",
			"lang": "ENG",
			"play": "https://jxjjxy-my.sharepoint.com/:u:/g/personal/dsznwgkc_m_mzr_me/EXDPNd-vtdBPpcS9KCOSPiYB8HaIEYZPaIo-0GfHmU5i-w?e=0UomK6&download=1"
		}, {
			"name": "Winnie the Pooh",
			"img": "'/img/moimg/184c.jpg'",
			"year": "2011",
			"lang": "ENG",
			"play": "https://jxjjxy-my.sharepoint.com/:u:/g/personal/dsznwgkc_m_mzr_me/EXDPNd-vtdBPpcS9KCOSPiYB8HaIEYZPaIo-0GfHmU5i-w?e=0UomK6&download=1"
		}, {
			"name": "Children Who Chase Lost Voices",
			"img": "'/img/moimg/185c.jpg'",
			"year": "2011",
			"lang": "ENG",
			"play": "https://jxjjxy-my.sharepoint.com/:u:/g/personal/dsznwgkc_m_mzr_me/EQ267BtQi9RAomUdkaKLI7IBfnWxHHmm0XTgohGPgOKuwg?e=1g8McZ&download=1"
		}, {
			"name": "Cars 2",
			"img": "'/img/moimg/186c.jpg'",
			"year": "2011",
			"lang": "ENG",
			"play": "https://jxjjxy-my.sharepoint.com/:u:/g/personal/dsznwgkc_m_mzr_me/ES_VUqwX0TRDl_lrC1mqKZkB4xI9nhwTk57wvjjYtHFrGw?e=hUiugz&download=1"
		}, {
			"name": "Kung Fu Panda 2",
			"img": "'/img/moimg/187c.jpg'",
			"year": "2011",
			"lang": "ENG",
			"play": "https://jxjjxy-my.sharepoint.com/:u:/g/personal/dsznwgkc_m_mzr_me/EYOd6-aoZQdEqSL6riWK7W8B6ebhdN0teK_C0IicXna7Gg?e=2yM7ne&download=1"
		}, {
			"name": "From Up on Poppy Hill",
			"img": "'/img/moimg/188c.jpg'",
			"year": "2011",
			"lang": "ENG",
			"play": "https://jxjjxy-my.sharepoint.com/:u:/g/personal/dsznwgkc_m_mzr_me/EbE4Tcfaah5OgpV3KKvTECYBOIVStsIv5Px2Qwx3DyxeEQ?e=8d0lKX&download=1"
		}, {
			"name": "The Smurfs",
			"img": "'/img/moimg/189c.jpg'",
			"year": "2011",
			"lang": "ENG",
			"play": "https://jxjjxy-my.sharepoint.com/:u:/g/personal/dsznwgkc_m_mzr_me/EWaIaI5wnZpJkvRP-LRhq48Bo5astfkOJkOtWX3g3B6pKQ?e=AJmMmw&download=1"
		}, {
			"name": "The Adventures of Tintin",
			"img": "'/img/moimg/190c.jpg'",
			"year": "2011",
			"lang": "ENG",
			"play": "https://jxjjxy-my.sharepoint.com/:u:/g/personal/dsznwgkc_m_mzr_me/ESvHVvN7M_1MpLTmB1BCEusBD-vqvxQDCrEC4awp8Uvynw?e=TEHg4b&download=1"
		}, {
			"name": "Puss in Boots",
			"img": "'/img/moimg/191c.jpg'",
			"year": "2011",
			"lang": "ENG",
			"play": "https://jxjjxy-my.sharepoint.com/:u:/g/personal/dsznwgkc_m_mzr_me/ESTC2NqaeEhGjKuYNoJX6-UByQYQu3-s_RVgEFsfjQWrYQ?e=Fh5XXi&download=1"
		}, {
			"name": "The Muppets",
			"img": "'/img/moimg/192c.jpg'",
			"year": "2011",
			"lang": "ENG",
			"play": "https://jxjjxy-my.sharepoint.com/:u:/g/personal/dsznwgkc_m_mzr_me/Eco9RXaxwBhBuNsU-hDFYP4BDSGaNhQUaA7Q-W6wiR6QDg?e=vfigk9&download=1"
		}, {
			"name": "Alvin and the Chipmunks: Chip-Wrecked",
			"img": "'/img/moimg/193c.jpg'",
			"year": "2011",
			"lang": "ENG",
			"play": "https://jxjjxy-my.sharepoint.com/:u:/g/personal/dsznwgkc_m_mzr_me/EX37QjtBQyhBrecKAGd9Mn0BQfASCZ4RMEkX_IcTBtdizQ?e=eXuhaQ&download=1"
		}, {
			"name": "How to Train Your Dragon",
			"img": "'/img/moimg/194c.jpg'",
			"year": "2010",
			"lang": "ENG",
			"play": "https://jxjjxy-my.sharepoint.com/:u:/g/personal/dsznwgkc_m_mzr_me/EV5HuGdeDyhCi_Cd9ahmBQEBj3wdSLoylNbIsTrHqTG9kg?e=m6qs9V&download=1"
		}, {
			"name": "Shrek Forever After",
			"img": "'/img/moimg/195c.jpg'",
			"year": "2010",
			"lang": "ENG",
			"play": "https://jxjjxy-my.sharepoint.com/:u:/g/personal/dsznwgkc_m_mzr_me/EYYo1afJU61BmJxrSYT8_sQB1o47EoLWUchVYK0C5j0EAA?e=EILQio&download=1"
		}, {
			"name": "Toy Story 3",
			"img": "'/img/moimg/196c.jpg'",
			"year": "2010",
			"lang": "ENG",
			"play": "https://jxjjxy-my.sharepoint.com/:u:/g/personal/dsznwgkc_m_mzr_me/EQATcTvXvutBr_-ljlxFYuoBJaCfKmI0Ade-XaCAivkFgA?e=EF4SWm&download=1"
		}, {
			"name": "Despicable Me",
			"img": "'/img/moimg/197c.jpg'",
			"year": "2010",
			"lang": "ENG",
			"play": "https://jxjjxy-my.sharepoint.com/:u:/g/personal/dsznwgkc_m_mzr_me/EX87cPGYfjZBgQBld8T1FPEBQJ-K7o9Xcs8Np5PBb8lhCA?e=A9Djr3&download=1"
		}, {
			"name": "Legend of The Guardians: The Owls of Ga'Hoole",
			"img": "'/img/moimg/198c.jpg'",
			"year": "2010",
			"lang": "ENG",
			"play": "https://jxjjxy-my.sharepoint.com/:u:/g/personal/dsznwgkc_m_mzr_me/EQ0qmTR3YttLuoHWOQgWXr4BOdZVskogXT4MBtBf3k04Ww?e=h5tzNz&download=1"
		}, {
			"name": "The Secret World of Arrietty",
			"img": "'/img/moimg/199c.jpg'",
			"year": "2010",
			"lang": "ENG",
			"play": "https://jxjjxy-my.sharepoint.com/:u:/g/personal/dsznwgkc_m_mzr_me/EbwVGs9EB0JLodM0_WTU4yYBSv15SpfUPZN6_UzdgbiAFg?e=ZLuKdE&download=1"
		}, {
			"name": "Alpha and Omega",
			"img": "'/img/moimg/200c.jpg'",
			"year": "2010",
			"lang": "ENG",
			"play": "https://jxjjxy-my.sharepoint.com/:u:/g/personal/dsznwgkc_m_mzr_me/EQ4kYRpKCO5Ig5F_EX7oP7wBLNeOQTMJVy-qrmWjjulghg?e=RRsT6G&download=1"
		}, {
			"name": "MegaMind",
			"img": "'/img/moimg/201c.jpg'",
			"year": "2010",
			"lang": "ENG",
			"play": "https://jxjjxy-my.sharepoint.com/:u:/g/personal/dsznwgkc_m_mzr_me/EVinop1UMy9ErTvA0QOb7G8BdEDXd-zpjxKFKU1VDUuouQ?e=PxfgHl&download=1"
		}, {
			"name": "Tangled",
			"img": "'/img/moimg/202c.jpg'",
			"year": "2010",
			"lang": "ENG",
			"play": "https://jxjjxy-my.sharepoint.com/:u:/g/personal/dsznwgkc_m_mzr_me/EVjVEw3FmgpKrSkRjraCwnUBHbi3PLXTUKdHiDid5p8hSQ?e=tc5e9q&download=1"
		}, {
			"name": "Yogi Bear",
			"img": "'/img/moimg/203c.jpg'",
			"year": "2010",
			"lang": "ENG",
			"play": "https://jxjjxy-my.sharepoint.com/:u:/g/personal/dsznwgkc_m_mzr_me/EXZiNJI7K05Flsw1tftITDcBuBuYSF9mQakCdwtV0MaKBw?e=R8kHMF&download=1"
		}, {
			"name": "Coraline",
			"img": "'/img/moimg/204c.jpg'",
			"year": "2009",
			"lang": "ENG",
			"play": "https://jxjjxy-my.sharepoint.com/:u:/g/personal/dsznwgkc_m_mzr_me/EZ7D_49QCUdCh0Jy9Ng_hBABz1rKYecMNDh4z6BT-xU8jA?e=YXmIvm&download=1"
		}, {
			"name": "Mary and Max",
			"img": "'/img/moimg/205c.jpg'",
			"year": "2009",
			"lang": "ENG",
			"play": "https://jxjjxy-my.sharepoint.com/:u:/g/personal/dsznwgkc_m_mzr_me/ERUCXLiutKZFg0KM9cXYNxwB2wfQW-SNUV4Zp_VBdydOGA?e=pvApG1&download=1"
		}, {
			"name": "The Secret of Kells",
			"img": "'/img/moimg/206c.jpg'",
			"year": "2009",
			"lang": "ENG",
			"play": "https://jxjjxy-my.sharepoint.com/:u:/g/personal/dsznwgkc_m_mzr_me/EfOOV9yzJcBCkmIHAtp0VKIByEzjACH8mtkx-HziYfwpTQ?e=VErLUU&download=1"
		}, {
			"name": "Monsters Vs Aliens",
			"img": "'/img/moimg/207c.jpg'",
			"year": "2009",
			"lang": "ENG",
			"play": "https://jxjjxy-my.sharepoint.com/:u:/g/personal/dsznwgkc_m_mzr_me/EVZrqgOTLrpLlEX93Cl2m6kBHHHzY5PwUcXN_3L7iGv02w?e=7YPea4&download=1"
		}, {
			"name": "Up",
			"img": "'/img/moimg/208c.jpg'",
			"year": "2009",
			"lang": "ENG",
			"play": "https://jxjjxy-my.sharepoint.com/:u:/g/personal/dsznwgkc_m_mzr_me/EUAMmRiHbOJNnDSrU6Fpkf8BaktGhKb-xNxvgOhALTEUiQ?e=v0ohbi&download=1"
		}, {
			"name": "Ice Age: Dawn of the Dinosaurs",
			"img": "'/img/moimg/209c.jpg'",
			"year": "2009",
			"lang": "ENG",
			"play": "https://jxjjxy-my.sharepoint.com/:u:/g/personal/dsznwgkc_m_mzr_me/ETcwvN-Lv4dAiAGSi6PjAfoBzIFL1uWjLdt28aG612yN5w?e=EKjX5C&download=1"
		}, {
			"name": "Summer Wars",
			"img": "'/img/moimg/210c.jpg'",
			"year": "2009",
			"lang": "ENG",
			"play": "https://jxjjxy-my.sharepoint.com/:u:/g/personal/dsznwgkc_m_mzr_me/EUlm9-DG22VBkrDvT6BBQSABSBJ4CEfbutTGyPab80C1yw?e=PSbGxI&download=1"
		}, {
			"name": "9",
			"img": "'/img/moimg/211c.jpg'",
			"year": "2009",
			"lang": "ENG",
			"play": "https://jxjjxy-my.sharepoint.com/:u:/g/personal/dsznwgkc_m_mzr_me/ETcgxAmgDd5Ekl5QrhYmMq4BZ7k5CRZghJvcoe49Scgecg?e=bQKYLl&download=1"
		}, {
			"name": "Cloudy with a Chance of Meatballs",
			"img": "'/img/moimg/212c.jpg'",
			"year": "2009",
			"lang": "ENG",
			"play": "https://jxjjxy-my.sharepoint.com/:u:/g/personal/dsznwgkc_m_mzr_me/EZ8eNAHD6YFBtPbZzHPZD9QBoLqDbwW9AazD6cmJvi87vw?e=iXqFRW&download=1"
		}, {
			"name": "Astro Boy",
			"img": "'/img/moimg/213c.jpg'",
			"year": "2009",
			"lang": "ENG",
			"play": "https://jxjjxy-my.sharepoint.com/:u:/g/personal/dsznwgkc_m_mzr_me/EcV5OBIPGWpAilA8-pNvPpwBrUZ7duGzd5z9952KO1vWuQ?e=iYvB5y&download=1"
		}, {
			"name": "A Christmas Carol",
			"img": "'/img/moimg/214c.jpg'",
			"year": "2009",
			"lang": "ENG",
			"play": "https://jxjjxy-my.sharepoint.com/:u:/g/personal/dsznwgkc_m_mzr_me/Ee_59iwdd29Lm5R7ZmmaIYIBEbEPRqjKxwWDk4FKFNeZtw?e=IFla5q&download=1"
		}, {
			"name": "The Princess and the Frog",
			"img": "'/img/moimg/215c.jpg'",
			"year": "2009",
			"lang": "ENG",
			"play": "https://jxjjxy-my.sharepoint.com/:u:/g/personal/dsznwgkc_m_mzr_me/Ea9F_w7w1chFonKrVWCIjuUB_E8Wj4jSqhpAFm__pMEBSQ?e=CaCBIA&download=1"
		}, {
			"name": "Alvin and The Chipmunks: The Squeakuel",
			"img": "'/img/moimg/216c.jpg'",
			"year": "2009",
			"lang": "ENG",
			"play": "https://jxjjxy-my.sharepoint.com/:u:/g/personal/dsznwgkc_m_mzr_me/Ebp6QomQA01FsaOXPSepppoBi_fdgdZmIta-zRZCdJS7Dg?e=sA6FI3&download=1"
		},
		{
			"name": "Horton Hears a Who",
			"img": "'/img/moimg/217c.jpg'",
			"year": "2008",
			"lang": "ENG",
			"play": "&download=1"
		}, {
			"name": "Kung Fu Panda",
			"img": "'/img/moimg/218c.jpg'",
			"year": "2008",
			"lang": "ENG",
			"play": "&download=1"
		}, {
			"name": "WALL-E",
			"img": "'/img/moimg/219c.jpg'",
			"year": "2008",
			"lang": "ENG",
			"play": "&download=1"
		}, {
			"name": "Ponyo",
			"img": "'/img/moimg/220c.jpg'",
			"year": "2008",
			"lang": "ENG",
			"play": "&download=1"
		}, {
			"name": "Madagascar: Escape 2 Africa",
			"img": "'/img/moimg/221c.jpg'",
			"year": "2008",
			"lang": "ENG",
			"play": "&download=1"
		}, {
			"name": "Bolt",
			"img": "'/img/moimg/222c.jpg'",
			"year": "2008",
			"lang": "ENG",
			"play": "&download=1"
		}, {
			"name": "The Tale of Despereaux",
			"img": "'/img/moimg/223c.jpg'",
			"year": "2008",
			"lang": "ENG",
			"play": "&download=1"
		}, {
			"name": "5 Centimeters per Second",
			"img": "'/img/moimg/224c.jpg'",
			"year": "2007",
			"lang": "ENG",
			"play": "&download=1"
		}, {
			"name": "Meet the Robinsons",
			"img": "'/img/moimg/225c.jpg'",
			"year": "2007",
			"lang": "ENG",
			"play": "&download=1"
		}, {
			"name": "Shrek the Third",
			"img": "'/img/moimg/226c.jpg'",
			"year": "2007",
			"lang": "ENG",
			"play": "&download=1"
		}, {
			"name": "Surf's Up",
			"img": "'/img/moimg/227c.jpg'",
			"year": "2007",
			"lang": "ENG",
			"play": "&download=1"
		}, {
			"name": "Ratatouille",
			"img": "'/img/moimg/228c.jpg'",
			"year": "2007",
			"lang": "ENG",
			"play": "&download=1"
		}, {
			"name": "Persepolis",
			"img": "'/img/moimg/229c.jpg'",
			"year": "2007",
			"lang": "ENG",
			"play": "&download=1"
		}, {
			"name": "The Simpsons Movie",
			"img": "'/img/moimg/230c.jpg'",
			"year": "2007",
			"lang": "ENG",
			"play": "&download=1"
		}, {
			"name": "Bee Movie",
			"img": "'/img/moimg/231c.jpg'",
			"year": "2007",
			"lang": "ENG",
			"play": "&download=1"
		}, {
			"name": "Beowulf",
			"img": "'/img/moimg/232c.jpg'",
			"year": "2007",
			"lang": "ENG",
			"play": "&download=1"
		}, {
			"name": "Alvin and the Chipmunks",
			"img": "'/img/moimg/233c.jpg'",
			"year": "2007",
			"lang": "ENG",
			"play": "&download=1"
		}
	]
}